ascii_data_file/__init__.py
ascii_data_file/ascii_data_file.py
ascii_data_file-1.dist-info/AUTHORS
ascii_data_file-1.dist-info/LICENSE
ascii_data_file-1.dist-info/METADATA
ascii_data_file-1.dist-info/WHEEL
ascii_data_file-1.dist-info/top_level.txt
ascii_data_file-1.dist-info/RECORD
